{
  "$schema": "https://raw.githubusercontent.com/microsoft/pyright/main/packages/vscode-pyright/schemas/pyrightconfig.schema.json",
  "include": [
    "src",
    "tests"
  ],
  "exclude": [
    "**/node_modules",
    "**/__pycache__",
    "**/.venv",
    "**/venv",
    "**/dist",
    "**/build",
    "**/htmlcov",
    "**/.pytest_cache",
    "**/alembic",
    "**/reports"
  ],
  "defineConstant": {
    "DEBUG": true
  },
  "stubPath": "stubs",
  "reportMissingImports": "warning",
  "reportMissingTypeStubs": false,
  "reportPrivateImportUsage": "warning",
  "reportUndefinedVariable": "error",
  "reportInvalidTypeForm": "error",
  "reportInvalidTypeArguments": "error",
  "reportIncompatibleVariableOverride": "warning",
  "reportIncompatibleMethodOverride": "warning",
  "reportUnusedImport": "warning",
  "reportUnusedClass": "warning",
  "reportUnusedFunction": "warning",
  "reportUnusedVariable": "warning",
  "reportDuplicateImport": "warning",
  "reportAbstractUsage": "warning",
  "reportAssertAlwaysTrue": "warning",
  "reportInvalidStringEscapeSequence": "error",
  "reportInvalidCast": "warning",
  "reportShadowedImports": "warning",
  "reportOptionalMemberAccess": "warning",
  "reportOptionalSubscript": "warning",
  "reportOptionalCall": "warning",
  "reportOptionalIterable": "warning",
  "reportOptionalContextManager": "warning",
  "reportOptionalOperand": "warning",
  "typeCheckingMode": "standard",
  "useLibraryCodeForTypes": true,
  "venvPath": ".",
  "venv": "venv"
}